Metadata-Version: 1.2
Name: botblocker
Version: 1.1.3
Summary: Python script to identify and block your bot followers on Twitter
Home-page: https://github.com/yanorestes/botblocker
Author: Yan Orestes
Author-email: yan.orestes@alura.com.br
License: MIT
Download-URL: https://github.com/yanorestes/botblocker/archive/1.1.3.zip
Keywords: twitter bot blocker tweepy botometer
Platform: UNKNOWN
Classifier: Development Status :: 4 - Beta
Classifier: Environment :: Console
Classifier: Intended Audience :: Developers
Classifier: Intended Audience :: End Users/Desktop
Classifier: License :: OSI Approved :: MIT License
Classifier: Natural Language :: English
Classifier: Natural Language :: Portuguese (Brazilian)
Classifier: Operating System :: OS Independent
Classifier: Programming Language :: Python :: 3
Classifier: Programming Language :: Python :: 3.4
Classifier: Programming Language :: Python :: 3.5
Classifier: Programming Language :: Python :: 3.6
Classifier: Programming Language :: Python :: 3.7
Classifier: Topic :: Internet
Requires-Python: >= 3.4
